chatgpt/__init__.py
chatgpt/__main__.py
chatgpt/snapshot.py
cli_dev_chat-0.2.0.dist-info/entry_points.txt
cli_dev_chat-0.2.0.dist-info/WHEEL
cli_dev_chat-0.2.0.dist-info/METADATA
cli_dev_chat-0.2.0.dist-info/RECORD
