Metadata-Version: 2.1
Name: cli-dev-chat
Version: 0.2.0
Summary: A command-line interface for interacting with OpenAI chat language models
License: MIT
Author: Jeremy Baron
Author-email: jbaron34@gmail.com
Requires-Python: >=3.6,<4.0
Classifier: License :: OSI Approved :: MIT License
Classifier: Programming Language :: Python :: 3
Classifier: Programming Language :: Python :: 3.6
Classifier: Programming Language :: Python :: 3.7
Classifier: Programming Language :: Python :: 3.8
Classifier: Programming Language :: Python :: 3.9
Classifier: Programming Language :: Python :: 3.10
Classifier: Programming Language :: Python :: 3.11
Requires-Dist: openai
